irawatch/__init__.py
irawatch/converter.py
irawatch/trace.py
irawatch/trace_pb2.py
irawatch-0.1.0.dist-info/METADATA
irawatch-0.1.0.dist-info/WHEEL
irawatch-0.1.0.dist-info/RECORD
