Metadata-Version: 2.4
Name: irawatch
Version: 0.1.0
Summary: IraWatch client for Python
Project-URL: Homepage, https://github.com/darylac/irawatch
Project-URL: Issues, https://github.com/darylac/irawatch/issues
Author-email: Daryl Correa <daryl.correa@epicode.in>
License-Expression: MIT
Requires-Python: >=3.8
Requires-Dist: nats-py>=2.9.0
Requires-Dist: protobuf>=5.29.3
